mathsip_turkmenogluc/MathOperations.py
mathsip_turkmenogluc/__init__.py
mathsip-1.0.0.dist-info/LICENSE
mathsip-1.0.0.dist-info/METADATA
mathsip-1.0.0.dist-info/WHEEL
mathsip-1.0.0.dist-info/top_level.txt
mathsip-1.0.0.dist-info/RECORD
